<annotation>
	<folder>FINAL_TEST</folder>
	<filename>21.jpg</filename>
	<path>D:\Object_Detection\ANPR\Tensorflow\workspace\images\FINAL_TEST\21.jpg</path>
	<source>
		<database>Unknown</database>
	</source>
	<size>
		<width>468</width>
		<height>366</height>
		<depth>3</depth>
	</size>
	<segmented>0</segmented>
	<object>
		<name>licence</name>
		<pose>Unspecified</pose>
		<truncated>0</truncated>
		<difficult>0</difficult>
		<bndbox>
			<xmin>62</xmin>
			<ymin>228</ymin>
			<xmax>180</xmax>
			<ymax>263</ymax>
		</bndbox>
	</object>
	<object>
		<name>car</name>
		<pose>Unspecified</pose>
		<truncated>1</truncated>
		<difficult>0</difficult>
		<bndbox>
			<xmin>5</xmin>
			<ymin>48</ymin>
			<xmax>468</xmax>
			<ymax>308</ymax>
		</bndbox>
	</object>
</annotation>
